pdf_chatter/__init__.py
pdf_chatter/agent.py
pdf_chatter/extract.py
pdf_chatter/main.py
pdf_chatter-0.1.5.dist-info/LICENSE
pdf_chatter-0.1.5.dist-info/METADATA
pdf_chatter-0.1.5.dist-info/WHEEL
pdf_chatter-0.1.5.dist-info/entry_points.txt
pdf_chatter-0.1.5.dist-info/RECORD
