Metadata-Version: 2.1
Name: pdf-chatter
Version: 0.1.5
Summary: LLM powered Q&A over extracted PDF text
Home-page: https://github.com/david-andrew/pdf-chatter
License: MIT
Author: David Samson
Author-email: david.andrew.engineer@gmail.com
Requires-Python: >=3.9
Classifier: License :: OSI Approved :: MIT License
Classifier: Programming Language :: Python :: 3
Classifier: Programming Language :: Python :: 3.9
Classifier: Programming Language :: Python :: 3.10
Classifier: Programming Language :: Python :: 3.11
Classifier: Programming Language :: Python :: 3.12
Requires-Dist: easyrepl (>=0.1.2)
Requires-Dist: nougat-ocr (>=0.1.17)
Requires-Dist: openai (>=1.12.0)
Project-URL: Bug Tracker, https://github.com/david-andrew/pdf-chatter/issues
